fancontrolbridge/__init__.py
fancontrolbridge/engine.py
fancontrolbridge/fancontrolbridge.py
fancontrolbridge/modules/__init__.py
fancontrolbridge/modules/fancontrollercommunicator/__init__.py
fancontrolbridge/modules/fancontrollercommunicator/commands.py
fancontrolbridge/modules/fancontrollercommunicator/errors.py
fancontrolbridge/modules/fancontrollercommunicator/main.py
fancontrolbridge/modules/fancontrollercommunicator/pyserialadapter.py
fancontrolbridge/modules/mqttmessenger/__init__.py
fancontrolbridge/modules/mqttmessenger/main.py
fancontrolbridge/modules/printstdoutput/__init__.py
fancontrolbridge/modules/printstdoutput/main.py
fancontrolbridge/modules/timestampinput/__init__.py
fancontrolbridge/modules/timestampinput/main.py
fancontrolbridge/utils/baseprocess.py
fancontrolbridge/utils/component.py
fancontrolbridge/utils/messagebroker.py
fancontrolbridge/utils/observable.py
fancontrolbridge-0.0.3.dist-info/LICENSE
fancontrolbridge-0.0.3.dist-info/METADATA
fancontrolbridge-0.0.3.dist-info/WHEEL
fancontrolbridge-0.0.3.dist-info/entry_points.txt
fancontrolbridge-0.0.3.dist-info/top_level.txt
fancontrolbridge-0.0.3.dist-info/RECORD
