Metadata-Version: 2.1
Name: fancontrolbridge
Version: 0.0.3
Summary: A MQTT-enabled bridge for the Arduino fan controller.
Author-email: Markus Ijäs <markus.ijas@pm.me>
License: GNU GENERAL PUBLIC LICENSE
Project-URL: Homepage, https://github.com/mtijas/mqtt-fancontroller
Project-URL: Bug Tracker, https://github.com/mtijas/mqtt-fancontroller/issues
Classifier: Programming Language :: Python :: 3
Classifier: License :: OSI Approved :: GNU General Public License v3 (GPLv3)
Classifier: Operating System :: OS Independent
Classifier: Development Status :: 3 - Alpha
Requires-Python: >=3.7
License-File: LICENSE
Requires-Dist: confuse
Requires-Dist: paho-mqtt
Requires-Dist: pyserial
